<?xml version="1.0" encoding="utf-8"?>
<abapGit version="v1.0.0" serializer="LCL_OBJECT_DSYS" serializer_version="v2.0.0">
 <asx:abap xmlns:asx="http://www.sap.com/abapxml" version="1.0">
  <asx:values>
   <LONGTEXTS>
    <item>
     <DOKIL>
      <ID>HY</ID>
      <OBJECT>SIMGCVI_DEFAULT_VALUES</OBJECT>
      <LANGU>D</LANGU>
      <TYP>E</TYP>
      <VERSION>0002</VERSION>
      <MASTERLANG>X</MASTERLANG>
      <TXTLINES>00012</TXTLINES>
      <DOKSTATE>A</DOKSTATE>
     </DOKIL>
     <HEAD>
      <TDOBJECT>DSYS</TDOBJECT>
      <TDNAME>SIMGCVI_DEFAULT_VALUES</TDNAME>
      <TDID>HY</TDID>
      <TDSPRAS>D</TDSPRAS>
      <TDFORM>S_DOCU_SHOW</TDFORM>
      <TDSTYLE>S_DOCUS1</TDSTYLE>
      <TDVERSION>00002</TDVERSION>
      <TDLINESIZE>072</TDLINESIZE>
     </HEAD>
     <LINES>
      <TLINE>
       <TDFORMAT>UT</TDFORMAT>
       <TDLINE>&amp;USE&amp;</TDLINE>
      </TLINE>
      <TLINE>
       <TDFORMAT>AS</TDFORMAT>
       <TDLINE>Dieses Business Add-In (BAdI) wird in der Komponente Stammdaten</TDLINE>
      </TLINE>
      <TLINE>
       <TDLINE>Synchronisation (AP-MD-BF-SYN) verwendet.</TDLINE>
      </TLINE>
      <TLINE>
       <TDFORMAT>*</TDFORMAT>
       <TDLINE>Mit diesem BAdI können Sie synchronisationsrelevante Felder der</TDLINE>
      </TLINE>
      <TLINE>
       <TDLINE>Debitoren-/Kreditorenintegration wie z.B. die Allgemeinen Daten des</TDLINE>
      </TLINE>
      <TLINE>
       <TDLINE>Debitors und buchungskreisabhängige Daten des Debitors bei Datenanlagen</TDLINE>
      </TLINE>
      <TLINE>
       <TDLINE>in der Richtung Geschäftspartner nach Debitor/Kreditor vorbelegen.</TDLINE>
      </TLINE>
      <TLINE>
       <TDFORMAT>*</TDFORMAT>
       <TDLINE>Das BAdI wird im Dialog zum Zeitpunkt ISDAT (Daten lesen) aufgerufen.</TDLINE>
      </TLINE>
      <TLINE>
       <TDFORMAT>UT</TDFORMAT>
       <TDLINE>&amp;PRECONDITIONS&amp;</TDLINE>
      </TLINE>
      <TLINE>
       <TDFORMAT>AS</TDFORMAT>
      </TLINE>
      <TLINE>
       <TDFORMAT>UT</TDFORMAT>
       <TDLINE>&amp;STANDARD_SETUP&amp;</TDLINE>
      </TLINE>
      <TLINE>
       <TDFORMAT>AS</TDFORMAT>
      </TLINE>
      <TLINE>
       <TDFORMAT>UT</TDFORMAT>
       <TDLINE>&amp;ACTIVITY&amp;</TDLINE>
      </TLINE>
      <TLINE>
       <TDFORMAT>AS</TDFORMAT>
      </TLINE>
      <TLINE>
       <TDFORMAT>UT</TDFORMAT>
       <TDLINE>&amp;EXAMPLE&amp;</TDLINE>
      </TLINE>
      <TLINE>
       <TDFORMAT>AS</TDFORMAT>
      </TLINE>
     </LINES>
    </item>
    <item>
     <DOKIL>
      <ID>HY</ID>
      <OBJECT>SIMGCVI_DEFAULT_VALUES</OBJECT>
      <LANGU>E</LANGU>
      <TYP>E</TYP>
      <VERSION>0002</VERSION>
      <TXTLINES>00008</TXTLINES>
      <DOKSTATE>A</DOKSTATE>
     </DOKIL>
     <HEAD>
      <TDOBJECT>DSYS</TDOBJECT>
      <TDNAME>SIMGCVI_DEFAULT_VALUES</TDNAME>
      <TDID>HY</TDID>
      <TDSPRAS>E</TDSPRAS>
      <TDFORM>S_DOCU_SHOW</TDFORM>
      <TDSTYLE>S_DOCUS1</TDSTYLE>
      <TDVERSION>00002</TDVERSION>
      <TDLINESIZE>072</TDLINESIZE>
     </HEAD>
     <LINES>
      <TLINE>
       <TDFORMAT>UT</TDFORMAT>
       <TDLINE>&amp;USE&amp;</TDLINE>
      </TLINE>
      <TLINE>
       <TDFORMAT>AS</TDFORMAT>
       <TDLINE>This Business Add-In (BAdI) is used in the Master Data Synchronization</TDLINE>
      </TLINE>
      <TLINE>
       <TDLINE>(AP-MD-BF-SYN) component.</TDLINE>
      </TLINE>
      <TLINE>
       <TDFORMAT>*</TDFORMAT>
       <TDLINE>With this BAdI you can set default fields for Customer/Vendor</TDLINE>
      </TLINE>
      <TLINE>
       <TDLINE>Integration that are relevant for synchronization, such as general data</TDLINE>
      </TLINE>
      <TLINE>
       <TDLINE>and company code data for the customer, when creating data in the</TDLINE>
      </TLINE>
      <TLINE>
       <TDLINE>direction business partner to customer/vendor.</TDLINE>
      </TLINE>
      <TLINE>
       <TDFORMAT>*</TDFORMAT>
       <TDLINE>The system calls the BAdI in online processing mode at the call-up point</TDLINE>
      </TLINE>
      <TLINE>
       <TDLINE>ISDAT (read data).</TDLINE>
      </TLINE>
      <TLINE>
       <TDFORMAT>UT</TDFORMAT>
       <TDLINE>&amp;PRECONDITIONS&amp;</TDLINE>
      </TLINE>
      <TLINE>
       <TDFORMAT>AS</TDFORMAT>
      </TLINE>
      <TLINE>
       <TDFORMAT>UT</TDFORMAT>
       <TDLINE>&amp;STANDARD_SETUP&amp;</TDLINE>
      </TLINE>
      <TLINE>
       <TDFORMAT>AS</TDFORMAT>
      </TLINE>
      <TLINE>
       <TDFORMAT>UT</TDFORMAT>
       <TDLINE>&amp;ACTIVITY&amp;</TDLINE>
      </TLINE>
      <TLINE>
       <TDFORMAT>AS</TDFORMAT>
      </TLINE>
      <TLINE>
       <TDFORMAT>UT</TDFORMAT>
       <TDLINE>&amp;EXAMPLE&amp;</TDLINE>
      </TLINE>
      <TLINE>
       <TDFORMAT>AS</TDFORMAT>
      </TLINE>
     </LINES>
    </item>
    <item>
     <DOKIL>
      <ID>HY</ID>
      <OBJECT>SIMGCVI_DEFAULT_VALUES</OBJECT>
      <LANGU>F</LANGU>
      <TYP>E</TYP>
      <VERSION>0002</VERSION>
      <TXTLINES>00009</TXTLINES>
      <DOKSTATE>A</DOKSTATE>
     </DOKIL>
     <HEAD>
      <TDOBJECT>DSYS</TDOBJECT>
      <TDNAME>SIMGCVI_DEFAULT_VALUES</TDNAME>
      <TDID>HY</TDID>
      <TDSPRAS>F</TDSPRAS>
      <TDFORM>S_DOCU_SHOW</TDFORM>
      <TDSTYLE>S_DOCUS1</TDSTYLE>
      <TDVERSION>00002</TDVERSION>
      <TDLINESIZE>072</TDLINESIZE>
     </HEAD>
     <LINES>
      <TLINE>
       <TDFORMAT>UT</TDFORMAT>
       <TDLINE>&amp;USE&amp;</TDLINE>
      </TLINE>
      <TLINE>
       <TDFORMAT>AS</TDFORMAT>
       <TDLINE>Ce Business Add-In (BAdI) est utilisé dans la composante Synchronisation</TDLINE>
      </TLINE>
      <TLINE>
       <TDLINE>de données de base (AP-MD-BF-SYN).</TDLINE>
      </TLINE>
      <TLINE>
       <TDFORMAT>*</TDFORMAT>
       <TDLINE>Il vous permet de prédéfinir les zones de l&apos;intégration client/</TDLINE>
      </TLINE>
      <TLINE>
       <TDLINE>fournisseur s&apos;appliquant à la synchronisation lors de la création de</TDLINE>
      </TLINE>
      <TLINE>
       <TDLINE>données dans le sens partenaire vers client/fournisseur. Il s&apos;agit par</TDLINE>
      </TLINE>
      <TLINE>
       <TDLINE>exemple de données client générales et de données client dépendantes de</TDLINE>
      </TLINE>
      <TLINE>
       <TDLINE>la société.</TDLINE>
      </TLINE>
      <TLINE>
       <TDFORMAT>*</TDFORMAT>
       <TDLINE>Appelez le BAdI dans le dialogue de l&apos;événement ISDAT (lecture des</TDLINE>
      </TLINE>
      <TLINE>
       <TDLINE>données).</TDLINE>
      </TLINE>
      <TLINE>
       <TDFORMAT>UT</TDFORMAT>
       <TDLINE>&amp;PRECONDITIONS&amp;</TDLINE>
      </TLINE>
      <TLINE>
       <TDFORMAT>AS</TDFORMAT>
      </TLINE>
      <TLINE>
       <TDFORMAT>UT</TDFORMAT>
       <TDLINE>&amp;STANDARD_SETUP&amp;</TDLINE>
      </TLINE>
      <TLINE>
       <TDFORMAT>AS</TDFORMAT>
      </TLINE>
      <TLINE>
       <TDFORMAT>UT</TDFORMAT>
       <TDLINE>&amp;ACTIVITY&amp;</TDLINE>
      </TLINE>
      <TLINE>
       <TDFORMAT>AS</TDFORMAT>
      </TLINE>
      <TLINE>
       <TDFORMAT>UT</TDFORMAT>
       <TDLINE>&amp;EXAMPLE&amp;</TDLINE>
      </TLINE>
      <TLINE>
       <TDFORMAT>AS</TDFORMAT>
      </TLINE>
     </LINES>
    </item>
   </LONGTEXTS>
  </asx:values>
 </asx:abap>
</abapGit>
